stisim/__init__.py
stisim/analyzers.py
stisim/calibration.py
stisim/demographics.py
stisim/networks.py
stisim/parameters.py
stisim/sim.py
stisim/utils.py
stisim/version.py
stisim/connectors/__init__.py
stisim/connectors/gud_syph.py
stisim/connectors/hiv_sti.py
stisim/data/__init__.py
stisim/data/downloaders.py
stisim/data/loaders.py
stisim/data/test_downloaders.py
stisim/diseases/__init__.py
stisim/diseases/bv.py
stisim/diseases/chlamydia.py
stisim/diseases/gonorrhea.py
stisim/diseases/gud.py
stisim/diseases/hiv.py
stisim/diseases/sti.py
stisim/diseases/syphilis.py
stisim/diseases/trichomoniasis.py
stisim/interventions/__init__.py
stisim/interventions/base_interventions.py
stisim/interventions/bv_interventions.py
stisim/interventions/gonorrhea_interventions.py
stisim/interventions/hiv_interventions.py
stisim/interventions/syphilis_interventions.py
stisim-1.4.0.dist-info/licenses/LICENSE
stisim-1.4.0.dist-info/METADATA
stisim-1.4.0.dist-info/WHEEL
stisim-1.4.0.dist-info/top_level.txt
stisim-1.4.0.dist-info/RECORD
