Metadata-Version: 2.4
Name: stisim
Version: 1.4.0
Summary: STI modelling toolbox built on the Starsim platform
Author: Alina Muellenmeister, Romesh Abeysuriya, Ryan Hull, Cliff Kerr, Jamie Cohen
Author-email: Robyn Stuart <info@starsim.org>
License: MIT License
Project-URL: Website, https://stisim.org
Project-URL: Source, https://github.com/starsimhub/stisim/
Keywords: agent-based model,simulation,disease,epidemiology,sexually transmitted infections,STIs,STDs
Classifier: Intended Audience :: Science/Research
Classifier: License :: OSI Approved :: MIT License
Classifier: Operating System :: OS Independent
Classifier: Programming Language :: Python
Classifier: Topic :: Software Development :: Libraries :: Python Modules
Classifier: Development Status :: 5 - Production/Stable
Classifier: Programming Language :: Python :: 3.10
Classifier: Programming Language :: Python :: 3.11
Classifier: Programming Language :: Python :: 3.12
Classifier: Programming Language :: Python :: 3.13
Requires-Python: >=3.9
License-File: LICENSE
Requires-Dist: starsim>=3.0.1
Requires-Dist: optuna
Requires-Dist: requests
Dynamic: license-file
